supSMSASM/__init__.py
supSMSASM/cli.py
supSMSASM/include/macros.inc
supSMSASM/ldscript/GMSE01.ld
supSMSASM/ldscript/GMSJ01.ld
supSMSASM/ldscript/GMSJ0A.ld
supSMSASM/ldscript/GMSP01.ld
supSMSASM/ldscript/common.ld
supSMSASM-0.1.1.dist-info/LICENSE
supSMSASM-0.1.1.dist-info/METADATA
supSMSASM-0.1.1.dist-info/WHEEL
supSMSASM-0.1.1.dist-info/entry_points.txt
supSMSASM-0.1.1.dist-info/top_level.txt
supSMSASM-0.1.1.dist-info/RECORD
