Metadata-Version: 2.1
Name: supSMSASM
Version: 0.1.1
Summary: A tool to make Gecko code from ASM for SMS
Home-page: https://github.com/sup39/supSMSASM
Author: sup39
Author-email: sms@sup39.dev
License: MIT
Project-URL: Bug Tracker, https://github.com/sup39/supSMSASM/issues
Classifier: Programming Language :: Python :: 3
Classifier: License :: OSI Approved :: MIT License
Requires-Python: >=3.8
License-File: LICENSE
